{
    "ping_all": {
        "command": "ansible -i /usr/share/ceph-ansible/hosts all -m ping",
        "cwd": null,
        "result": 0,
        "time_stamp": "2021-06-09-17-09"
    },
    "device_alias": {
        "command": "ansible-playbook -i /usr/share/ceph-ansible/hosts device-alias.yml",
        "cwd": "/usr/share/ceph-ansible",
        "result": 0,
        "time_stamp": "2021-06-09-17-10"
    },
    "deploy_core": {
        "command": "ansible-playbook core.yml",
        "cwd": "/usr/share/ceph-ansible",
        "result": 0,
        "time_stamp": "2021-06-09-17-19"
    }
}